snakecamel/__init__.py
snakecamel/camelize.py
snakecamel/snakeize.py
snakecamel-0.1.0.dist-info/LICENSE.md
snakecamel-0.1.0.dist-info/WHEEL
snakecamel-0.1.0.dist-info/METADATA
snakecamel-0.1.0.dist-info/RECORD
