Metadata-Version: 2.1
Name: snakecamel
Version: 0.1.0
Summary: An easy-to-use package to convert to camelCase or snake_case
Home-page: https://github.com/lysnikolaou/snakecamel
License: MIT
Keywords: snakecase,camelcase
Author: Lysandros Nikolaou
Author-email: lisandrosnik@gmail.com
Requires-Python: >=3.10,<4.0
Classifier: Development Status :: 3 - Alpha
Classifier: License :: OSI Approved :: MIT License
Classifier: Programming Language :: Python :: 3
Classifier: Programming Language :: Python :: 3 :: Only
Classifier: Programming Language :: Python :: 3.10
Classifier: Topic :: Software Development :: Libraries
Classifier: Topic :: Text Processing :: General
Project-URL: Documentation, https://github.com/lysnikolaou/snakecamel
Project-URL: Repository, https://github.com/lysnikolaou/snakecamel
